textplusstuff/__init__.py
textplusstuff/__version__.py
textplusstuff/admin.py
textplusstuff/apps.py
textplusstuff/datastructures.py
textplusstuff/exceptions.py
textplusstuff/fields.py
textplusstuff/models.py
textplusstuff/registry.py
textplusstuff/serializers.py
textplusstuff/signals.py
textplusstuff/widgets.py
textplusstuff/migrations/0001_initial.py
textplusstuff/migrations/0002_auto_20151104_1648.py
textplusstuff/migrations/__init__.py
textplusstuff/parser/__init__.py
textplusstuff/parser/lexer.py
textplusstuff/parser/nodes.py
textplusstuff/parser/parser.py
textplusstuff/parser/tokens.py
textplusstuff/south_migrations/0001_initial.py
textplusstuff/south_migrations/__init__.py
textplusstuff/static/textplusstuff/darkly/bootstrap.min.css
textplusstuff/static/textplusstuff/fonts/glyphicons-halflings-regular.eot
textplusstuff/static/textplusstuff/fonts/glyphicons-halflings-regular.svg
textplusstuff/static/textplusstuff/fonts/glyphicons-halflings-regular.ttf
textplusstuff/static/textplusstuff/fonts/glyphicons-halflings-regular.woff
textplusstuff/templates/textplusstuff/api.html
textplusstuff/templates/textplusstuff/change_form_with_renditions.html
textplusstuff/views/__init__.py
textplusstuff/views/mixins.py
textplusstuff/views/renderers.py
django_textplusstuff-0.7.1.dist-info/LICENSE
django_textplusstuff-0.7.1.dist-info/METADATA
django_textplusstuff-0.7.1.dist-info/WHEEL
django_textplusstuff-0.7.1.dist-info/top_level.txt
django_textplusstuff-0.7.1.dist-info/RECORD
