Metadata-Version: 2.1
Name: django-textplusstuff
Version: 0.7.1
Summary: A django field that makes it easy to intersperse 'stuff' into blocks of text.
Home-page: http://github.com/WGBH/django-textplusstuff/
Author: Jonathan Ellenberger et al
Author-email: jay_thompson@wgbh.org
License: MIT License, see LICENSE
Platform: UNKNOWN
Classifier: Framework :: Django
Classifier: License :: OSI Approved :: MIT License
Classifier: Natural Language :: English
Classifier: Programming Language :: Python
Classifier: Programming Language :: Python :: 2
Classifier: Programming Language :: Python :: 2.7
Classifier: Programming Language :: Python :: 3
Classifier: Programming Language :: Python :: 3.6
Classifier: Programming Language :: Python :: 3.7
Classifier: Topic :: Text Processing :: Markup
Classifier: Development Status :: 4 - Beta
Requires-Dist: beautifulsoup4 (==4.4.0)
Requires-Dist: djangorestframework (>=2.4.8)
Requires-Dist: markdown2 (>=2.3.0)
